aug_pd_cdk/__init__.py
aug_pd_cdk/py.typed
aug_pd_cdk/_jsii/__init__.py
aug_pd_cdk/_jsii/aug-pd-ckd@0.0.2.jsii.tgz
aug_pd_cdk-0.0.2.dist-info/LICENSE
aug_pd_cdk-0.0.2.dist-info/METADATA
aug_pd_cdk-0.0.2.dist-info/WHEEL
aug_pd_cdk-0.0.2.dist-info/top_level.txt
aug_pd_cdk-0.0.2.dist-info/RECORD
